kukajto_downloader/__init__.py
kukajto_downloader/constants.py
kukajto_downloader/exceptions.py
kukajto_downloader/scraper.py
kukajto_downloader/wrapper.py
kukajto_downloader/web/__init__.py
kukajto_downloader/web/__main__.py
kukajto_downloader/web/constants.py
kukajto_downloader/web/assets/Ubuntu-Regular.ttf
kukajto_downloader/web/assets/favicon.ico
kukajto_downloader/web/assets/favicon.png
kukajto_downloader/web/assets/index.html
kukajto_downloader/web/assets/script.js
kukajto_downloader/web/assets/style.css
kukajto_downloader-1.2.2.dist-info/LICENSE
kukajto_downloader-1.2.2.dist-info/METADATA
kukajto_downloader-1.2.2.dist-info/WHEEL
kukajto_downloader-1.2.2.dist-info/entry_points.txt
kukajto_downloader-1.2.2.dist-info/top_level.txt
kukajto_downloader-1.2.2.dist-info/RECORD
