Metadata-Version: 2.1
Name: kukajto-downloader
Version: 1.2.2
Summary: This program can find the direct url of a video or subtitle file from kukaj.io.
Author-email: Juraj Honsch <jurakin.dev@gmail.com>
Project-URL: Homepage, https://github.com/jurakin/kukajto-downloader
Project-URL: Bug Tracker, https://github.com/jurakin/kukajto-downloader/issues
Classifier: Programming Language :: Python :: 3
Classifier: License :: OSI Approved :: MIT License
Classifier: Operating System :: Microsoft :: Windows
Requires-Python: >=3.7
License-File: LICENSE
Requires-Dist: selenium >=4.7
Requires-Dist: webdriver-manager
Requires-Dist: eel
